country_server.py
country_server-1.0.1.dist-info/METADATA
country_server-1.0.1.dist-info/WHEEL
country_server-1.0.1.dist-info/entry_points.txt
country_server-1.0.1.dist-info/top_level.txt
country_server-1.0.1.dist-info/RECORD
