Metadata-Version: 2.4
Name: country-server
Version: 1.0.1
Summary: A simple MCP country-lookup server
Requires-Python: >=3.8
Requires-Dist: fastapi
Requires-Dist: uvicorn
Requires-Dist: sse-starlette
